sqlsaber/__init__.py
sqlsaber/__main__.py
sqlsaber/api.py
sqlsaber/agents/__init__.py
sqlsaber/agents/base.py
sqlsaber/agents/handoff_agent.py
sqlsaber/agents/provider_factory.py
sqlsaber/agents/pydantic_ai_agent.py
sqlsaber/application/__init__.py
sqlsaber/application/auth_setup.py
sqlsaber/application/db_setup.py
sqlsaber/application/model_selection.py
sqlsaber/application/prompts.py
sqlsaber/cli/__init__.py
sqlsaber/cli/auth.py
sqlsaber/cli/buffered_streaming.py
sqlsaber/cli/commands.py
sqlsaber/cli/completers.py
sqlsaber/cli/database.py
sqlsaber/cli/display.py
sqlsaber/cli/html_export.py
sqlsaber/cli/interactive.py
sqlsaber/cli/memory.py
sqlsaber/cli/models.py
sqlsaber/cli/onboarding.py
sqlsaber/cli/slash_commands.py
sqlsaber/cli/streaming.py
sqlsaber/cli/theme.py
sqlsaber/cli/threads.py
sqlsaber/cli/update_check.py
sqlsaber/cli/usage.py
sqlsaber/config/__init__.py
sqlsaber/config/api_keys.py
sqlsaber/config/auth.py
sqlsaber/config/database.py
sqlsaber/config/logging.py
sqlsaber/config/providers.py
sqlsaber/config/settings.py
sqlsaber/database/__init__.py
sqlsaber/database/base.py
sqlsaber/database/csv.py
sqlsaber/database/csvs.py
sqlsaber/database/duckdb.py
sqlsaber/database/mysql.py
sqlsaber/database/postgresql.py
sqlsaber/database/resolver.py
sqlsaber/database/schema.py
sqlsaber/database/sqlite.py
sqlsaber/memory/__init__.py
sqlsaber/memory/manager.py
sqlsaber/memory/storage.py
sqlsaber/prompts/__init__.py
sqlsaber/prompts/claude.py
sqlsaber/prompts/dangerous_mode.py
sqlsaber/prompts/handoff.py
sqlsaber/prompts/memory.py
sqlsaber/prompts/openai.py
sqlsaber/theme/__init__.py
sqlsaber/theme/manager.py
sqlsaber/threads/__init__.py
sqlsaber/threads/manager.py
sqlsaber/threads/storage.py
sqlsaber/tools/__init__.py
sqlsaber/tools/base.py
sqlsaber/tools/display.py
sqlsaber/tools/registry.py
sqlsaber/tools/sql_guard.py
sqlsaber/tools/sql_tools.py
sqlsaber/utils/__init__.py
sqlsaber/utils/json_utils.py
sqlsaber-0.53.0.dist-info/METADATA
sqlsaber-0.53.0.dist-info/WHEEL
sqlsaber-0.53.0.dist-info/entry_points.txt
sqlsaber-0.53.0.dist-info/licenses/LICENSE
sqlsaber-0.53.0.dist-info/RECORD
