Metadata-Version: 2.4
Name: sqlsaber
Version: 0.53.0
Summary: SQLsaber - Open-source agentic SQL assistant
License-File: LICENSE
Requires-Python: >=3.12
Requires-Dist: aiomysql>=0.2.0
Requires-Dist: aiosqlite>=0.21.0
Requires-Dist: asyncpg>=0.30.0
Requires-Dist: cyclopts>=3.22.1
Requires-Dist: duckdb>=0.9.2
Requires-Dist: httpx>=0.28.1
Requires-Dist: keyring>=25.6.0
Requires-Dist: keyrings-cryptfile; sys_platform == 'linux'
Requires-Dist: platformdirs>=4.0.0
Requires-Dist: prompt-toolkit>3.0.51
Requires-Dist: pydantic-ai
Requires-Dist: questionary>=2.1.0
Requires-Dist: rich>=13.7.0
Requires-Dist: sqlglot[rs]>=27.20.0
Requires-Dist: structlog>=25.4.0
Requires-Dist: tabulate>=0.9.0
